DynamoBase.py
dynamobase-1.0.0.dist-info/LICENSE
dynamobase-1.0.0.dist-info/METADATA
dynamobase-1.0.0.dist-info/WHEEL
dynamobase-1.0.0.dist-info/top_level.txt
dynamobase-1.0.0.dist-info/RECORD
