Metadata-Version: 2.1
Name: dynamobase
Version: 1.0.0
Summary: A Json Model that is the easiest way to query DynamoDB.
Author-email: Jaguar <jack.v.yang@gmail.com>
Project-URL: Homepage, https://github.com/jaguaryang/dynamo-base
Project-URL: Bug Tracker, https://github.com/jaguaryang/dynamo-base/issues
Classifier: Programming Language :: Python :: 3
Classifier: License :: OSI Approved :: MIT License
Classifier: Operating System :: OS Independent
Requires-Python: >=3.7
License-File: LICENSE
Requires-Dist: boto3 (==1.24.68)
Requires-Dist: simplejson (==3.17.6)
